comp/__init__.py
comp/exceptions.py
comp/leaders.py
comp/sample.py
comp/lead/__init__.py
comp/tests/__init__.py
comp/tests/test.py
comp_lead/__init__.py
comp_lead/companies.py
comp_lead/exceptions.py
comp_lead/leaders.py
comp_lead/sample.py
comp_lead/lead/__init__.py
comp_lead/tests/__init__.py
comp_lead/tests/test.py
comp_lead-0.1.15.dist-info/METADATA
comp_lead-0.1.15.dist-info/WHEEL
comp_lead-0.1.15.dist-info/top_level.txt
comp_lead-0.1.15.dist-info/RECORD
