Metadata-Version: 2.1
Name: comp-lead
Version: 0.1.15
Summary: Display a handful of tech leaders and companies
Home-page: https://github.com/endormi/comp-lead
Author: Endormi
Author-email: contactendormi@gmail.com
License: UNKNOWN
Platform: UNKNOWN
Classifier: Programming Language :: Python :: 3
Classifier: License :: OSI Approved :: MIT License
Classifier: Operating System :: OS Independent
Requires-Python: >=3
